[{"handle":"BryanSinger","text":"RT Marisol97313751: Thanks for mentioning me, I am back on twitter, https://t.co/AX4LUUbtB0","date":"Mon Nov 19 02:25:08 +0000 2018","user_id":"1057221927994081280"},{"handle":"BryanSinger","text":"RT EmmaXDMercury: Thanks for mentioning me, I am back on twitter, https://t.co/0EsoNN8gkI","date":"Mon Nov 19 02:25:07 +0000 2018","user_id":"1057221927994081280"},{"handle":"BryanSinger","text":"Thanks for the mention! Marisol97313751: Love you! You're the best!","date":"Mon Nov 19 02:23:27 +0000 2018","user_id":"1057221927994081280"},{"handle":"BryanSinger","text":"Thanks for the mention! EmmaXDMercury: Love you! You're the best!","date":"Mon Nov 19 02:23:26 +0000 2018","user_id":"1057221927994081280"},{"handle":"BryanSinger","text":"Thanks for the mention! tattoojo: Love you! You're the best!","date":"Mon Nov 19 02:18:16 +0000 2018","user_id":"1057221927994081280"},{"handle":"BryanSinger","text":"RT AmbroseEdwin7: Thanks for mentioning me, I am back on twitter, https://t.co/T2rkQTJ6Ya","date":"Mon Nov 19 02:15:36 +0000 2018","user_id":"1057221927994081280"},{"handle":"BryanSinger","text":"RT tattoojo: Thanks for mentioning me, I am back on twitter, https://t.co/wIol7jfW8n","date":"Mon Nov 19 02:15:36 +0000 2018","user_id":"1057221927994081280"},{"handle":"BryanSinger","text":"Thanks for the mention! mercurybitch: Love you! You're the best!","date":"Mon Nov 19 02:13:12 +0000 2018","user_id":"1057221927994081280"},{"handle":"BryanSinger","text":"Thanks for the mention! everra: Love you! You're the best!","date":"Mon Nov 19 02:13:11 +0000 2018","user_id":"1057221927994081280"},{"handle":"BryanSinger","text":"Thanks for the mention! dustbittter: Love you! You're the best!","date":"Mon Nov 19 02:13:11 +0000 2018","user_id":"1057221927994081280"},{"handle":"BryanSinger","text":"RT everra: Thanks for mentioning me, I am back on twitter, https://t.co/lL6Sriflhm","date":"Mon Nov 19 02:10:11 +0000 2018","user_id":"1057221927994081280"},{"handle":"BryanSinger","text":"RT Philip_Roper: Thanks for mentioning me, I am back on twitter, https://t.co/f5ohUgt0Ya","date":"Mon Nov 19 02:10:11 +0000 2018","user_id":"1057221927994081280"},{"handle":"BryanSinger","text":"Thanks for the mention! AmbroseEdwin7: Love you! You're the best!","date":"Mon Nov 19 02:08:09 +0000 2018","user_id":"1057221927994081280"},{"handle":"BryanSinger","text":"Thanks for the mention! Philip_Roper: Love you! You're the best!","date":"Mon Nov 19 02:08:09 +0000 2018","user_id":"1057221927994081280"},{"handle":"BryanSinger","text":"RT AmbroseEdwin7: Thanks for mentioning me, I am back on twitter, https://t.co/i2iyfQ7JLz","date":"Mon Nov 19 02:05:10 +0000 2018","user_id":"1057221927994081280"},{"handle":"BryanSinger","text":"RT RenatoContreraz: Thanks for mentioning me, I am back on twitter, https://t.co/GPkjgTOKP1","date":"Mon Nov 19 02:05:09 +0000 2018","user_id":"1057221927994081280"},{"handle":"BryanSinger","text":"RT movieguy82: Thanks for mentioning me, I am back on twitter, https://t.co/SN9ADGlJCy","date":"Mon Nov 19 02:05:08 +0000 2018","user_id":"1057221927994081280"},{"handle":"BryanSinger","text":"RT RenatoContreraz: Thanks for mentioning me, I am back on twitter, https://t.co/SlGtobtk6y","date":"Mon Nov 19 02:05:08 +0000 2018","user_id":"1057221927994081280"},{"handle":"BryanSinger","text":"Thanks for the mention! movieguy82: Love you! You're the best!","date":"Mon Nov 19 02:03:30 +0000 2018","user_id":"1057221927994081280"},{"handle":"BryanSinger","text":"Thanks for the mention! RenatoContreraz: Love you! You're the best!","date":"Mon Nov 19 02:03:29 +0000 2018","user_id":"1057221927994081280"},{"handle":"BryanSinger","text":"Thanks for the mention! beautyfinn: Love you! You're the best!","date":"Mon Nov 19 02:03:28 +0000 2018","user_id":"1057221927994081280"},{"handle":"BryanSinger","text":"Thanks for the mention! DrBrianMay: Love you! You're the best!","date":"Mon Nov 19 02:03:28 +0000 2018","user_id":"1057221927994081280"},{"handle":"BryanSinger","text":"RT DrBrianMay: Thanks for mentioning me, I am back on twitter, https://t.co/f0V6rP5K4k","date":"Mon Nov 19 02:00:41 +0000 2018","user_id":"1057221927994081280"},{"handle":"BryanSinger","text":"#RT @UniStudios: @jwilliamson48 Hi Jamie, we are so sorry for any inconvenience. If you're still here in the Park, please DM your phone number so we can find out a little more about what happened.","date":"Mon Nov 19 01:31:20 +0000 2018","user_id":"1057221927994081280"},{"handle":"BryanSinger","text":"#RT @UniStudios: @valerie_kircher Hello again, Valerie. If you would like for one of our Guest Relations team to reach out to you, please DM your phone number, and we will gladly give you a call.","date":"Mon Nov 19 01:31:19 +0000 2018","user_id":"1057221927994081280"},{"handle":"BryanSinger","text":"#RT @UniStudios: All aboard the Hogwarts Express! #WizardingWorldHollywood https://t.co/fbvj9NQ4YB","date":"Mon Nov 19 01:31:19 +0000 2018","user_id":"1057221927994081280"},{"handle":"BryanSinger","text":"#RT @UniStudios: @valerie_kircher If you would like to discuss this further, please DM your phone number, and one of our Guest Relations team will reach out to you.","date":"Mon Nov 19 01:31:19 +0000 2018","user_id":"1057221927994081280"},{"handle":"BryanSinger","text":"#RT @UniStudios: @valerie_kircher Hi Valerie, we understand your concern and apologize for your disappointment. I believe you spoke with a Lead and a Supervisor, and the pass you were offered is what we have available. We will share your concerns about that with the appropri…","date":"Mon Nov 19 01:31:18 +0000 2018","user_id":"1057221927994081280"},{"handle":"BryanSinger","text":"RT valerie_kircher: Thanks for mentioning me, I am back on twitter, https://t.co/xjhfJ4F1E5","date":"Sun Nov 18 23:40:24 +0000 2018","user_id":"1057221927994081280"},{"handle":"BryanSinger","text":"Thanks for the mention! valerie_kircher: Love you! You're the best!","date":"Sun Nov 18 23:38:14 +0000 2018","user_id":"1057221927994081280"},{"handle":"BryanSinger","text":"RT valerie_kircher: Thanks for mentioning me, I am back on twitter, https://t.co/OJ46CZ8OvT","date":"Sun Nov 18 23:35:21 +0000 2018","user_id":"1057221927994081280"},{"handle":"BryanSinger","text":"#RT @UniStudios: @valerie_kircher Hello Valerie, we're so sorry to hear about this. Are you in the Park now?","date":"Sun Nov 18 23:31:23 +0000 2018","user_id":"1057221927994081280"},{"handle":"BryanSinger","text":"#RT @UniStudios: How many minions can you find? 🤔 https://t.co/nQ4jExnFdq","date":"Sun Nov 18 23:31:23 +0000 2018","user_id":"1057221927994081280"},{"handle":"BryanSinger","text":"#RT @UniStudios: @K8Carol On behalf of Optimus Prime and the Autobots, we thank you!","date":"Sun Nov 18 23:31:22 +0000 2018","user_id":"1057221927994081280"},{"handle":"BryanSinger","text":"#RT @UniStudios: @hapaniki Wingardium leviosa . . . and you're flying! It's like magic!","date":"Sun Nov 18 23:31:22 +0000 2018","user_id":"1057221927994081280"},{"handle":"BryanSinger","text":"#RT @UniStudios: Sunday Funday at Krustyland! 🤡 https://t.co/c3fRjBZ7jr","date":"Sun Nov 18 23:31:21 +0000 2018","user_id":"1057221927994081280"},{"handle":"BryanSinger","text":"Thanks for the mention! ppfilippi: Love you! You're the best!","date":"Sun Nov 18 22:18:26 +0000 2018","user_id":"1057221927994081280"},{"handle":"BryanSinger","text":"RT ppfilippi: Thanks for mentioning me, I am back on twitter, https://t.co/aiGvKJmKPd","date":"Sun Nov 18 22:16:19 +0000 2018","user_id":"1057221927994081280"},{"handle":"BryanSinger","text":"Thanks for the mention! FlicksAndFlix: Love you! You're the best!","date":"Sun Nov 18 21:38:27 +0000 2018","user_id":"1057221927994081280"},{"handle":"BryanSinger","text":"#RT @UniStudios: Magical treats, spellbinding sweets, and so much more await you at Honeydukes! https://t.co/USZqWbc8bS","date":"Sun Nov 18 21:31:24 +0000 2018","user_id":"1057221927994081280"},{"handle":"BryanSinger","text":"#RT @UniStudios: @K8Carol Did you save the Allspark???","date":"Sun Nov 18 21:31:23 +0000 2018","user_id":"1057221927994081280"},{"handle":"BryanSinger","text":"RT FlicksAndFlix: Thanks for mentioning me, I am back on twitter, https://t.co/xvPzsf7q5O","date":"Sun Nov 18 21:30:32 +0000 2018","user_id":"1057221927994081280"},{"handle":"BryanSinger","text":"Thanks for the mention! Queen4everBlog: Love you! You're the best!","date":"Sun Nov 18 20:53:34 +0000 2018","user_id":"1057221927994081280"},{"handle":"BryanSinger","text":"#RT @UniStudios: Going to the Park with your BFF this weekend &gt; any other plans you might have had https://t.co/p3Of0hmCWt","date":"Sun Nov 18 19:31:18 +0000 2018","user_id":"1057221927994081280"},{"handle":"BryanSinger","text":"#RT @UniStudios: Too early for a Squishee? Never. https://t.co/priMoONO6Q","date":"Sun Nov 18 19:31:17 +0000 2018","user_id":"1057221927994081280"},{"handle":"BryanSinger","text":"#RT @UniStudios: We found three kids who are setting the bar for what it means to be bold. Stay tuned this week for their incredible stories. https://t.co/oHtLi656Y3","date":"Sun Nov 18 17:31:24 +0000 2018","user_id":"1057221927994081280"},{"handle":"BryanSinger","text":"RT cannes  : Thanks!","date":"Sun Nov 18 10:34:07 +0000 2018","user_id":"1057221927994081280"},{"handle":"BryanSinger","text":"#RT @UniStudios: What's your favorite part of Revenge of the Mummy? 🎢 https://t.co/jlbV66qmUB","date":"Sun Nov 18 01:31:08 +0000 2018","user_id":"1057221927994081280"},{"handle":"BryanSinger","text":"#RT @UniStudios: Our happy place. 😄 https://t.co/1rqORS0IWy","date":"Sun Nov 18 01:31:08 +0000 2018","user_id":"1057221927994081280"},{"handle":"BryanSinger","text":"#RT @UniStudios: @thefunmachine Hi John. We're sorry to hear about this! Will you DM us a screen shot of what you are seeing on the web page so we can look into it?","date":"Sun Nov 18 01:31:07 +0000 2018","user_id":"1057221927994081280"},{"handle":"BryanSinger","text":"#RT @UniStudios: For those of you who haven't visited us in a while... https://t.co/pNHywLWKSs","date":"Sat Nov 17 23:31:19 +0000 2018","user_id":"1057221927994081280"},{"handle":"BryanSinger","text":"#RT @UniStudios: @GlendaVee Mmmmm.....donuts 🤤🍩\n\nDon't forget to save us a bite!","date":"Sat Nov 17 23:31:18 +0000 2018","user_id":"1057221927994081280"},{"handle":"BryanSinger","text":"#RT @UniStudios: Relationship Goals 😍 https://t.co/TnAsSw1g0D","date":"Sat Nov 17 23:31:18 +0000 2018","user_id":"1057221927994081280"},{"handle":"BryanSinger","text":"#RT @UniStudios: @GlendaVee We are firm believers that calories NEVER count when you're at a theme park! We hope you and your son enjoy a fun day filled with tasty treats! 😋","date":"Sat Nov 17 21:31:33 +0000 2018","user_id":"1057221927994081280"},{"handle":"BryanSinger","text":"#RT @UniStudios: Have you tried Butterbeer Ice Cream yet? #WizardingWorldHollywood https://t.co/uTggweTotV","date":"Sat Nov 17 21:31:33 +0000 2018","user_id":"1057221927994081280"},{"handle":"BryanSinger","text":"#RT @UniStudios: @JinteChristina Hello! While the new attraction is coming in 2019, we do not have an approximate opening date just yet. Be sure to check back at https://t.co/4p52cgGgPd for updates as we draw closer to your visit!","date":"Sat Nov 17 21:31:32 +0000 2018","user_id":"1057221927994081280"},{"handle":"BryanSinger","text":"#RT @UniStudios: @FreeSpirit_888 You can view the schedule for the Spanish tour here: https://t.co/J5koOlEvFh\n\nThe schedule is updated weekly.","date":"Sat Nov 17 21:31:31 +0000 2018","user_id":"1057221927994081280"},{"handle":"BryanSinger","text":"#RT @UniStudios: Get ready to experience the holidays like never before at the Park this season! https://t.co/z5taPJVqcU","date":"Sat Nov 17 19:31:32 +0000 2018","user_id":"1057221927994081280"},{"handle":"BryanSinger","text":"#RT @UniStudios: We’re “fall”-ing in love with this apple cinnamon crepe.😋 🍎 https://t.co/ZtUEQtqC1C","date":"Sat Nov 17 19:31:31 +0000 2018","user_id":"1057221927994081280"},{"handle":"BryanSinger","text":"#RT @UniStudios: @FreeSpirit_888 Hi there! While we do not currently offer the VIP Experience in Spanish, our World Famous Studio Tour is offered in Spanish at select times every day!","date":"Sat Nov 17 17:31:28 +0000 2018","user_id":"1057221927994081280"},{"handle":"BryanSinger","text":"RT cannes  : Thanks!","date":"Sat Nov 17 16:34:07 +0000 2018","user_id":"1057221927994081280"},{"handle":"BryanSinger","text":"#RT @UniStudios: Use an emoji to describe how you feel when you see this classic sign! https://t.co/r9mNlB7pzo","date":"Sat Nov 17 03:31:29 +0000 2018","user_id":"1057221927994081280"},{"handle":"BryanSinger","text":"#RT @UniStudios: Leaving the office on Friday like... https://t.co/SoPMmdpKoz","date":"Sat Nov 17 01:31:24 +0000 2018","user_id":"1057221927994081280"},{"handle":"BryanSinger","text":"#RT @UniStudios: 🎶 It's #FreezeRayFriday, gotta try this smoothie today...🎶 https://t.co/nG51b2HJ0y","date":"Sat Nov 17 01:31:23 +0000 2018","user_id":"1057221927994081280"},{"handle":"BryanSinger","text":"#RT @UniStudios: When enjoying Springfield U.S.A., stop by Krusty Burger for one of the best burgers in town! 🍔 https://t.co/Ei8WSoa2J8","date":"Fri Nov 16 23:31:11 +0000 2018","user_id":"1057221927994081280"},{"handle":"BryanSinger","text":"#RT @UniStudios: JUST ANNOUNCED: The mischievous Minions are joining us for a 5K run through the Park! Lace up your sneakers, stretch your legs, and get ready for Running Universal – coming in May 2019! https://t.co/yomJMpCmGP https://t.co/p1v6oWkfpc","date":"Fri Nov 16 21:31:21 +0000 2018","user_id":"1057221927994081280"},{"handle":"BryanSinger","text":"Thanks for the mention! SomeGuyJerry: Love you! You're the best!","date":"Fri Nov 16 21:23:29 +0000 2018","user_id":"1057221927994081280"},{"handle":"BryanSinger","text":"RT SomeGuyJerry: Thanks for mentioning me, I am back on twitter, https://t.co/Yk0jC2cj2y","date":"Fri Nov 16 21:15:54 +0000 2018","user_id":"1057221927994081280"},{"handle":"BryanSinger","text":"#RT @UniStudios: Magical treats, spellbinding sweets, and so much more await you at Honeydukes! https://t.co/L6BzYjNqUJ","date":"Fri Nov 16 19:31:21 +0000 2018","user_id":"1057221927994081280"},{"handle":"BryanSinger","text":"RT GilliamReport: Thanks for mentioning me, I am back on twitter, https://t.co/Wfr9FVI07J","date":"Fri Nov 16 18:15:55 +0000 2018","user_id":"1057221927994081280"},{"handle":"BryanSinger","text":"RT ray_bastien: Thanks for mentioning me, I am back on twitter, https://t.co/KTVgbxHwWE","date":"Fri Nov 16 17:55:46 +0000 2018","user_id":"1057221927994081280"},{"handle":"BryanSinger","text":"RT GilliamReport: Thanks for mentioning me, I am back on twitter, https://t.co/t2cjPD0b2K","date":"Fri Nov 16 17:55:46 +0000 2018","user_id":"1057221927994081280"},{"handle":"BryanSinger","text":"Thanks for the mention! ray_bastien: Love you! You're the best!","date":"Fri Nov 16 17:53:41 +0000 2018","user_id":"1057221927994081280"},{"handle":"BryanSinger","text":"RT GilliamReport: Thanks for mentioning me, I am back on twitter, https://t.co/qwSpLJR9bk","date":"Fri Nov 16 17:45:36 +0000 2018","user_id":"1057221927994081280"},{"handle":"BryanSinger","text":"#RT @UniStudios: Who's coming to see us this weekend? 😄 https://t.co/QdMkELHWUt","date":"Fri Nov 16 17:31:40 +0000 2018","user_id":"1057221927994081280"},{"handle":"BryanSinger","text":"RT GilliamReport: Thanks for mentioning me, I am back on twitter, https://t.co/8dbqh0bUgx","date":"Fri Nov 16 17:30:53 +0000 2018","user_id":"1057221927994081280"},{"handle":"BryanSinger","text":"Thanks for the mention! GilliamReport: Love you! You're the best!","date":"Fri Nov 16 17:28:21 +0000 2018","user_id":"1057221927994081280"},{"handle":"BryanSinger","text":"#RT @UniStudios: It's everything you love about WaterWorld, in video game form! Except for the \"soak zone,\" of course. 💦 https://t.co/1OXKwy6ePt","date":"Fri Nov 16 01:27:09 +0000 2018","user_id":"1057221927994081280"},{"handle":"BryanSinger","text":"#RT @UniStudios: What do you think they like to talk about? 🐝🚚 https://t.co/g0JENwmjlM","date":"Fri Nov 16 01:27:09 +0000 2018","user_id":"1057221927994081280"},{"handle":"BryanSinger","text":"RT DutchTeacher78: Thanks for mentioning me, I am back on twitter, https://t.co/B0aAWXigMT","date":"Thu Nov 15 23:43:28 +0000 2018","user_id":"1057221927994081280"},{"handle":"BryanSinger","text":"RT DutchTeacher78: Thanks for mentioning me, I am back on twitter, https://t.co/XHazQqXZbL","date":"Thu Nov 15 23:43:27 +0000 2018","user_id":"1057221927994081280"},{"handle":"BryanSinger","text":"Thanks for the mention! DutchTeacher78: Love you! You're the best!","date":"Thu Nov 15 23:43:14 +0000 2018","user_id":"1057221927994081280"},{"handle":"BryanSinger","text":"#RT @UniStudios: Ride or die. Take down rivals and collect iconic #FastFurious cars in Fast &amp; Furious Takedown! Pre-register today to earn in-game rewards at launch. Coming soon to the App Store &amp; Google Play: https://t.co/nDhXsp1sAE https://t.co/bx9dHI4Lh0","date":"Thu Nov 15 23:27:08 +0000 2018","user_id":"1057221927994081280"},{"handle":"BryanSinger","text":"#RT @UniStudios: Popcorn on a smoothie? Now you have our attention. https://t.co/LW4k5GXO83","date":"Thu Nov 15 23:27:07 +0000 2018","user_id":"1057221927994081280"},{"handle":"BryanSinger","text":"#RT @UniStudios: WARNING: Do not watch while hungry. 😋😋 https://t.co/DfWIWwoGjo","date":"Thu Nov 15 21:27:19 +0000 2018","user_id":"1057221927994081280"},{"handle":"BryanSinger","text":"#RT @UniStudios: All aboard the Hogwarts Express! #WizardingWorldHollywood https://t.co/Mh6F3Qr0RM","date":"Thu Nov 15 19:27:16 +0000 2018","user_id":"1057221927994081280"},{"handle":"BryanSinger","text":"#RT @UniStudios: Attention, Pass Members! The entire Universal Classic Monsters Collection has arrived on Blu-ray, and you can win one for yourself! LAST CHANCE TO ENTER! Sweepstakes ends at 5pm PST: https://t.co/7Gvfl7mvwI https://t.co/l3sVuJ5YwE","date":"Thu Nov 15 19:27:15 +0000 2018","user_id":"1057221927994081280"},{"handle":"BryanSinger","text":"#RT @UniStudios: @EHuffmanRealtor Hello, Eugene! Thank you for reaching out! If you have a question regarding the season pass, please feel free to direct message us and we would be happy to assist you.","date":"Thu Nov 15 19:27:15 +0000 2018","user_id":"1057221927994081280"},{"handle":"BryanSinger","text":"#RT @UniStudios: Attention, Pass Members! The entire Universal Classic Monsters Collection has arrived on Blu-ray, and you can win one for yourself! Enter now, if you dare: https://t.co/ge7Dmy6cSn https://t.co/OwkDRM7KyC","date":"Thu Nov 15 03:27:12 +0000 2018","user_id":"1057221927994081280"},{"handle":"BryanSinger","text":"#RT @UniStudios: RT @HPWizardsUnite: It’s up to you to protect the wizarding world. Enlist immediately for the Statute of Secrecy Task Force: https://t.co/XN4DmTQY7R #WizardsUnite https://t.co/poYnYlVGyn","date":"Thu Nov 15 01:27:46 +0000 2018","user_id":"1057221927994081280"},{"handle":"BryanSinger","text":"RT ray_bastien: Thanks for mentioning me, I am back on twitter, https://t.co/bgY948Tam2","date":"Thu Nov 15 00:08:28 +0000 2018","user_id":"1057221927994081280"},{"handle":"BryanSinger","text":"Thanks for the mention! ray_bastien: Love you! You're the best!","date":"Wed Nov 14 23:53:17 +0000 2018","user_id":"1057221927994081280"},{"handle":"BryanSinger","text":"RT ray_bastien: Thanks for mentioning me, I am back on twitter, https://t.co/drWh1CbvNu","date":"Wed Nov 14 23:48:25 +0000 2018","user_id":"1057221927994081280"},{"handle":"BryanSinger","text":"#RT @UniStudios: Have you tried Butterbeer Ice Cream yet? #WizardingWorldHollywood https://t.co/fPuWjjsiY7","date":"Wed Nov 14 23:27:41 +0000 2018","user_id":"1057221927994081280"},{"handle":"BryanSinger","text":"#RT @UniStudios: Who can resist a delicious Squishee when visiting Springfield, USA? https://t.co/zWqsG25Qao","date":"Wed Nov 14 23:27:41 +0000 2018","user_id":"1057221927994081280"},{"handle":"BryanSinger","text":"#RT @UniStudios: For those of you who haven't visited us in a while... https://t.co/B0jQhbAueA","date":"Wed Nov 14 21:27:37 +0000 2018","user_id":"1057221927994081280"},{"handle":"BryanSinger","text":"#RT @UniStudios: It's never too early to awaken an ancient curse... ☠️ https://t.co/aKL7WnviMe","date":"Wed Nov 14 19:27:13 +0000 2018","user_id":"1057221927994081280"},{"handle":"BryanSinger","text":"#RT @UniStudios: Have you met Gru yet? https://t.co/lZ6xcdsgdr","date":"Wed Nov 14 19:27:13 +0000 2018","user_id":"1057221927994081280"},{"handle":"BryanSinger","text":"#RT @UniStudios: Every day can be #TacoTuesday in Springfield, USA. 🐝🌮 https://t.co/5tyB14iaGk","date":"Wed Nov 14 03:27:22 +0000 2018","user_id":"1057221927994081280"},{"handle":"BryanSinger","text":"#RT @UniStudios: Cotton candy, mini doughnuts, lollipops… and that’s just in one sundae. https://t.co/G01d5o9WZ9","date":"Wed Nov 14 01:27:35 +0000 2018","user_id":"1057221927994081280"}]