[{"handle":"PerezHilton","text":"This. Is. Not. Ok. https://t.co/7fmWxlM6uR","date":"Mon Jun 27 01:40:02 +0000 2022","user_id":"19329393"},{"handle":"PerezHilton","text":"Texas is threatening Lyft and... https://t.co/GLP1jCvOrA","date":"Mon Jun 27 01:15:01 +0000 2022","user_id":"19329393"},{"handle":"PerezHilton","text":"A true miracle!!!","date":"Mon Jun 27 00:35:22 +0000 2022","user_id":"19329393"},{"handle":"PerezHilton","text":"Kendall Jenner seems to be loving life as a newly single woman! https://t.co/swH6l5NB8l","date":"Sun Jun 26 22:47:12 +0000 2022","user_id":"19329393"},{"handle":"PerezHilton","text":"Do U see the resemblance??? https://t.co/eF3iVmFJmD","date":"Sun Jun 26 22:29:28 +0000 2022","user_id":"19329393"},{"handle":"PerezHilton","text":"Who else thinks Elon Musk is lying about this? #GhislaineMaxwell","date":"Sun Jun 26 21:57:57 +0000 2022","user_id":"19329393"},{"handle":"PerezHilton","text":"Jodie Sweetin is speaking out after video of her being slammed down into the ground by police while protesting for abortion rights goes viral. Details HERE: https://t.co/sYLfNi27tK","date":"Sun Jun 26 21:36:15 +0000 2022","user_id":"19329393"},{"handle":"PerezHilton","text":"This song feels more relevant now than when Beyonce released it on Tuesday. It's got a whole heftier political subtext! #BreakMySoul","date":"Sun Jun 26 21:03:20 +0000 2022","user_id":"19329393"},{"handle":"PerezHilton","text":"Winona Ryder has no plans on getting hitched to her \"soulmate\" Scott Mackinlay Hahn anytime soon! Here's why: https://t.co/GXG2vuzBvN","date":"Sun Jun 26 20:30:00 +0000 2022","user_id":"19329393"},{"handle":"PerezHilton","text":"#Twilight's Peter Facinelli and Lily Anne Harrison are expecting their first child together! https://t.co/yrE1zvMVbY","date":"Sun Jun 26 19:58:04 +0000 2022","user_id":"19329393"},{"handle":"PerezHilton","text":"Beloved TikTok star Ophelia Nichols, also known as Mama Tot, is pleading for answers after her son was shot and killed one day before his birthday. https://t.co/0gbQ9o8Och","date":"Sun Jun 26 19:19:54 +0000 2022","user_id":"19329393"},{"handle":"PerezHilton","text":"Oh no! Bam Margera has been reported missing again! https://t.co/DCaCfW9XL9","date":"Sun Jun 26 17:54:01 +0000 2022","user_id":"19329393"},{"handle":"PerezHilton","text":"This is absolutely horrific. \nhttps://t.co/F4VQW2Rrz9","date":"Sun Jun 26 16:31:17 +0000 2022","user_id":"19329393"},{"handle":"PerezHilton","text":"Olivia Rodrigo has one thing to say to the Supreme Court Justices who overturned Roe v. Wade -- \"F**k You.\" https://t.co/ADtzwECztH","date":"Sun Jun 26 14:58:53 +0000 2022","user_id":"19329393"},{"handle":"PerezHilton","text":"Jeffrey Epstein's accomplice put on suicide watch, BUT... her lawyer says she's not suicidal. #GhislaineMaxwell https://t.co/4syDzXH8OP","date":"Sun Jun 26 06:45:01 +0000 2022","user_id":"19329393"},{"handle":"PerezHilton","text":"Harry Styles would approve! #MargotRobbie #Barbie","date":"Sun Jun 26 06:20:59 +0000 2022","user_id":"19329393"},{"handle":"PerezHilton","text":"After a life-long battle with lymphedema, #Bachelorette alum Cam Ayala revealed he had his leg amputated. https://t.co/LzcmWLRQev","date":"Sat Jun 25 23:16:34 +0000 2022","user_id":"19329393"},{"handle":"PerezHilton","text":"Well, this customer certainly got more than what they bargained for... \nhttps://t.co/zFKTsb3GxN","date":"Sat Jun 25 22:24:43 +0000 2022","user_id":"19329393"},{"handle":"PerezHilton","text":"The first solo project from one of the members of BTS has been announced following their hiatus announcement! Details HERE: https://t.co/0VnWTJX8cD","date":"Sat Jun 25 21:58:52 +0000 2022","user_id":"19329393"},{"handle":"PerezHilton","text":"Kristin Cavallari’s sons have some hilarious dating advice for their momma! Details HERE: https://t.co/O9q6i0vlH7","date":"Sat Jun 25 21:07:55 +0000 2022","user_id":"19329393"},{"handle":"PerezHilton","text":"This is wild - literally!","date":"Sat Jun 25 20:27:44 +0000 2022","user_id":"19329393"},{"handle":"PerezHilton","text":"The latest in the Spears family feud... \nhttps://t.co/s7BoSXC4ID","date":"Sat Jun 25 20:02:40 +0000 2022","user_id":"19329393"},{"handle":"PerezHilton","text":"Religion is the root of so much evil! https://t.co/EZR2stZGme","date":"Sat Jun 25 19:53:47 +0000 2022","user_id":"19329393"},{"handle":"PerezHilton","text":"I think your trans 18 year old, Vivian, may disagree. #ElonMusk","date":"Sat Jun 25 19:00:04 +0000 2022","user_id":"19329393"},{"handle":"PerezHilton","text":"In the wake of the Supreme Court's decision to overturn Roe v. Wade, Meadow Walker got real about her own abortion story. Details HERE: https://t.co/5KGbEk2DyA","date":"Sat Jun 25 18:51:57 +0000 2022","user_id":"19329393"},{"handle":"PerezHilton","text":"Harries STILL refuse to believe that this is a real relationship. They think Harry Styles and Olivia Wilde are dating for publicity. Loonies! https://t.co/38v3DWH9eE","date":"Sat Jun 25 18:25:41 +0000 2022","user_id":"19329393"},{"handle":"PerezHilton","text":"This is SHAMEFUL! Transparency is essential! #Uvalde","date":"Sat Jun 25 18:16:27 +0000 2022","user_id":"19329393"},{"handle":"PerezHilton","text":"Very suspicious. The attorney for Gabby Petito's family claims Roberta Laundrie sent a letter to her son Brian containing \"some pretty extreme things.\" Details HERE: \nhttps://t.co/vhTS378oPJ","date":"Sat Jun 25 17:53:23 +0000 2022","user_id":"19329393"},{"handle":"PerezHilton","text":"So many Celebrity Breakups in the first half of 2022! https://t.co/ZtDQ6RJMSO","date":"Sat Jun 25 17:44:14 +0000 2022","user_id":"19329393"},{"handle":"PerezHilton","text":"Who do you believe?? https://t.co/9dPCnNpdlZ","date":"Sat Jun 25 16:59:56 +0000 2022","user_id":"19329393"},{"handle":"PerezHilton","text":"Being in Ukraine right now is dangerous. No? Well, Ben Stiller....","date":"Sat Jun 25 16:30:18 +0000 2022","user_id":"19329393"},{"handle":"PerezHilton","text":"#DWTS pro Cheryl Burke is opening up about her abortion story. https://t.co/xoHg1yZxVJ","date":"Sat Jun 25 16:10:06 +0000 2022","user_id":"19329393"},{"handle":"PerezHilton","text":"This tweet feels especially relevant now! #SallyField #IvankaTrump","date":"Sat Jun 25 15:45:11 +0000 2022","user_id":"19329393"},{"handle":"PerezHilton","text":"A group of 15 women filming the reality series Bad Girls Gone God had to be rescued from a deadly hiking trail! https://t.co/IWjYDXUJDS","date":"Sat Jun 25 14:53:57 +0000 2022","user_id":"19329393"},{"handle":"PerezHilton","text":"ICYMI: All the furious reactions to the horrifying Roe v Wade news... https://t.co/Vl0UIZ7koN","date":"Sat Jun 25 08:28:43 +0000 2022","user_id":"19329393"},{"handle":"PerezHilton","text":"Because he’s not the head of he Muslim faith? 🤦‍♂️ #PopeFrancis","date":"Sat Jun 25 07:11:55 +0000 2022","user_id":"19329393"},{"handle":"PerezHilton","text":"Rita Moreno's awful story was all too common in the days before Roe v Wade. And it was almost so much worse! https://t.co/c8SLkgbdEW","date":"Sat Jun 25 01:13:30 +0000 2022","user_id":"19329393"},{"handle":"PerezHilton","text":"Everything leaving Netflix next month... https://t.co/9BR7ksvfq2","date":"Sat Jun 25 01:01:44 +0000 2022","user_id":"19329393"},{"handle":"PerezHilton","text":"Anna Faris keeps it real and raw when discussing being twice divorced. https://t.co/qL8k0zkkzt","date":"Sat Jun 25 00:41:05 +0000 2022","user_id":"19329393"},{"handle":"PerezHilton","text":"Such a heartbreaking exit. We wish all the best for her! https://t.co/HdXtGLLC94","date":"Sat Jun 25 00:11:52 +0000 2022","user_id":"19329393"},{"handle":"PerezHilton","text":"Wow! Seriously though, how long until Republicans make *this* illegal?? https://t.co/K0dOqEg0lQ","date":"Fri Jun 24 23:59:53 +0000 2022","user_id":"19329393"},{"handle":"PerezHilton","text":"Good news for a lot of ladies out there! Khloé talked Kim into fixing SKIMS! https://t.co/RWf62la5gn","date":"Fri Jun 24 23:48:32 +0000 2022","user_id":"19329393"},{"handle":"PerezHilton","text":"Will Amber Heard even try to appeal if this is what it takes?? https://t.co/ACgKM01zMU","date":"Fri Jun 24 23:14:48 +0000 2022","user_id":"19329393"},{"handle":"PerezHilton","text":"We almost got more Lauren Conrad -- but she decided she's DONE with reality TV! https://t.co/z2MazqzChB","date":"Fri Jun 24 22:32:35 +0000 2022","user_id":"19329393"},{"handle":"PerezHilton","text":"Murder confession SHOCKER! Brian Laundrie claimed Gabby Petito was injured on hike! https://t.co/9ZUaVljhRO","date":"Fri Jun 24 22:01:41 +0000 2022","user_id":"19329393"},{"handle":"PerezHilton","text":"Billie: Nobody's gonna know... they're gonna know. How would they know?  https://t.co/88NJbM026r","date":"Fri Jun 24 21:52:31 +0000 2022","user_id":"19329393"},{"handle":"PerezHilton","text":"Who could do this to a child? Let alone her granddaughter?? https://t.co/MqBiBqs5iz","date":"Fri Jun 24 21:13:10 +0000 2022","user_id":"19329393"},{"handle":"PerezHilton","text":"OMFG!!!! https://t.co/xQnhJGbBlD","date":"Fri Jun 24 20:41:54 +0000 2022","user_id":"19329393"},{"handle":"PerezHilton","text":"Wow. WTF, Ceaser Emanuel?? https://t.co/WPXolcGP10","date":"Fri Jun 24 20:20:53 +0000 2022","user_id":"19329393"},{"handle":"PerezHilton","text":"Zachary Levi faced hard times very recently. Happy he is doing better. https://t.co/zeikpeTA5z","date":"Fri Jun 24 20:00:51 +0000 2022","user_id":"19329393"},{"handle":"PerezHilton","text":"Kelly Clarkson must feel so relieved!\nhttps://t.co/azWkD8iHaP","date":"Fri Jun 24 19:42:10 +0000 2022","user_id":"19329393"},{"handle":"PerezHilton","text":"Tobey Maguire's ex is SO happy to be his EX! \nhttps://t.co/JTP7BOmNrk","date":"Fri Jun 24 19:26:37 +0000 2022","user_id":"19329393"},{"handle":"PerezHilton","text":"Nobody should be above the law! \nhttps://t.co/LEktPrFVvv","date":"Fri Jun 24 19:04:08 +0000 2022","user_id":"19329393"},{"handle":"PerezHilton","text":"There it is.","date":"Fri Jun 24 18:47:31 +0000 2022","user_id":"19329393"},{"handle":"PerezHilton","text":"Jessie James Decker reveals she's struggling with depression and body image in raw, emotional post: \nhttps://t.co/cshOOtGGDI","date":"Fri Jun 24 18:40:04 +0000 2022","user_id":"19329393"},{"handle":"PerezHilton","text":"Make no mistake. They will be coming for birth control and IVF next. All while blocking legislation that would improve quality of life for children and mothers. But guns? Weapons of death? Never. https://t.co/Vl0UIZ7koN","date":"Fri Jun 24 18:14:41 +0000 2022","user_id":"19329393"},{"handle":"PerezHilton","text":"WARNING: POTENTIALLY TRIGGERING CONTENT \nhttps://t.co/3BfJLtWs67","date":"Fri Jun 24 17:54:26 +0000 2022","user_id":"19329393"},{"handle":"PerezHilton","text":"Oh no!! #Cheer star Maddy Brum got hit by a car! \nhttps://t.co/rsRTxL2wLJ","date":"Fri Jun 24 17:30:26 +0000 2022","user_id":"19329393"},{"handle":"PerezHilton","text":"It's a #SouthernCharm scandal! \nhttps://t.co/Cjy4GOzE9Y","date":"Fri Jun 24 17:06:44 +0000 2022","user_id":"19329393"},{"handle":"PerezHilton","text":"BIG yikes! https://t.co/G2lwaPcA0d","date":"Fri Jun 24 16:28:02 +0000 2022","user_id":"19329393"},{"handle":"PerezHilton","text":"Not sure God can help when you are a convicted criminal! https://t.co/z1l19kU1lI","date":"Fri Jun 24 16:01:04 +0000 2022","user_id":"19329393"},{"handle":"PerezHilton","text":"\"How do you think victims feel when they see this Anna?\" https://t.co/nwZkB7y085","date":"Fri Jun 24 15:36:02 +0000 2022","user_id":"19329393"},{"handle":"PerezHilton","text":"Sharon Stone has been through so much. https://t.co/z86JekemtP","date":"Fri Jun 24 15:11:56 +0000 2022","user_id":"19329393"},{"handle":"PerezHilton","text":"Camille Vasquez keeps getting great press! https://t.co/FREmbMdEpI","date":"Fri Jun 24 14:52:10 +0000 2022","user_id":"19329393"},{"handle":"PerezHilton","text":"We saw this coming, and yet it still hurts so deeply. Reminder that this will not stop abortions. It just stops safe access to them. And rich people will continue to get them without consequence. https://t.co/EeqDrAHW4x","date":"Fri Jun 24 14:43:42 +0000 2022","user_id":"19329393"},{"handle":"PerezHilton","text":"This is sickening!! https://t.co/ldDGizZcjs","date":"Fri Jun 24 14:31:10 +0000 2022","user_id":"19329393"},{"handle":"PerezHilton","text":"Chris Daughtry lost two of his loved ones very close together. Unimaginable pain. https://t.co/WMIxThEPj7","date":"Fri Jun 24 14:10:21 +0000 2022","user_id":"19329393"},{"handle":"PerezHilton","text":"Camp North!! 🏕️  https://t.co/UQJKP2fkoP","date":"Fri Jun 24 13:40:59 +0000 2022","user_id":"19329393"},{"handle":"PerezHilton","text":"There have been SO many celebrity splits in 2022 so far... get a full recap of all the heartbreak here: https://t.co/ZtDQ6Rsc1g","date":"Fri Jun 24 13:15:22 +0000 2022","user_id":"19329393"},{"handle":"PerezHilton","text":"Harry Styles brought the #pride to his London show!","date":"Fri Jun 24 03:32:14 +0000 2022","user_id":"19329393"},{"handle":"PerezHilton","text":"Ew ew ewwwwww!!!!! Kete!!!!!!!! \nhttps://t.co/ylzibMLx9S","date":"Fri Jun 24 03:05:01 +0000 2022","user_id":"19329393"},{"handle":"PerezHilton","text":"Queens! LITERALLY the best two to every do it! #LilKim #MaryJBlige","date":"Fri Jun 24 02:32:21 +0000 2022","user_id":"19329393"},{"handle":"PerezHilton","text":"Matt Gaetz's \"any &amp; all things\" pardon pleas revealed -- and Twitter is living for it!\nhttps://t.co/Evv03MoKpD","date":"Fri Jun 24 01:38:02 +0000 2022","user_id":"19329393"},{"handle":"PerezHilton","text":"Okay so Alexa is a portal to the paranormal now?! https://t.co/y6uquGdP8q","date":"Fri Jun 24 01:19:55 +0000 2022","user_id":"19329393"},{"handle":"PerezHilton","text":"Aww! Jonah Hill's sister Beanie Feldstein is getting married to her longtime love! \nhttps://t.co/mKUuTUNCai","date":"Fri Jun 24 01:09:42 +0000 2022","user_id":"19329393"},{"handle":"PerezHilton","text":"Has the media learned nothing when it comes to Britney Spears? \nhttps://t.co/WxvjMGMxIi","date":"Fri Jun 24 00:55:43 +0000 2022","user_id":"19329393"},{"handle":"PerezHilton","text":"Dad dies by suicide after billionaire drunk driver who killed his 3 children was released from jail on Father's Day weekend: \nhttps://t.co/GaaWFr1LGd","date":"Fri Jun 24 00:33:37 +0000 2022","user_id":"19329393"},{"handle":"PerezHilton","text":"From #farmlife to #marriedlife, CONGRATS to Adrian Grenier! https://t.co/eN4n3xwlsS","date":"Fri Jun 24 00:18:16 +0000 2022","user_id":"19329393"},{"handle":"PerezHilton","text":"Angelina INSISTS she didn't cheat! And she has receipts! #JerseyShore \nhttps://t.co/XxHMYm7FUC","date":"Fri Jun 24 00:03:49 +0000 2022","user_id":"19329393"},{"handle":"PerezHilton","text":"Ray Liotta's fiancee opens up weeks after his passing: \nhttps://t.co/WZp0hkZGhl","date":"Thu Jun 23 23:54:57 +0000 2022","user_id":"19329393"},{"handle":"PerezHilton","text":"Wow. Brian Laundries' parents keep being like this! \nhttps://t.co/Qp8chnDZQr","date":"Thu Jun 23 23:22:36 +0000 2022","user_id":"19329393"},{"handle":"PerezHilton","text":"Another report on Ezra Miller has come out... thoughts? \nhttps://t.co/xwQQzyIVy1","date":"Thu Jun 23 23:06:51 +0000 2022","user_id":"19329393"},{"handle":"PerezHilton","text":"Sweet baby Zen would have turned 1 this week. \nhttps://t.co/Gi0FRN1Cw5","date":"Thu Jun 23 22:41:31 +0000 2022","user_id":"19329393"},{"handle":"PerezHilton","text":"Oklahoma, are y'all really like this??? #Lightyear #LGBTQ \nhttps://t.co/6yfSslNpS1","date":"Thu Jun 23 21:59:12 +0000 2022","user_id":"19329393"},{"handle":"PerezHilton","text":"DENISE RICHARDS JUST JOINED ONLYFANS!!  #WildThings247 https://t.co/aI5hsoMrbz","date":"Thu Jun 23 21:28:39 +0000 2022","user_id":"19329393"},{"handle":"PerezHilton","text":"Where did they go wrong?? #TheKardashians \nhttps://t.co/Pc61aqNmvS","date":"Thu Jun 23 21:14:38 +0000 2022","user_id":"19329393"},{"handle":"PerezHilton","text":"Okkkkurrr Khloé. We see you!! https://t.co/Q5rk3bt4FG","date":"Thu Jun 23 20:42:11 +0000 2022","user_id":"19329393"},{"handle":"PerezHilton","text":"Is Ben Affleck someone who just enjoys options, or is he an agent of chaos? https://t.co/BAxPG3e9Xm","date":"Thu Jun 23 20:23:46 +0000 2022","user_id":"19329393"},{"handle":"PerezHilton","text":"The judge SHOULD make this permanent! Absolutely ridiculous it was granted to the father in the first place! \nhttps://t.co/dK29r7cAue","date":"Thu Jun 23 19:43:45 +0000 2022","user_id":"19329393"},{"handle":"PerezHilton","text":"What world are we living in, honestly! https://t.co/7HS0joZhSV","date":"Thu Jun 23 19:28:34 +0000 2022","user_id":"19329393"},{"handle":"PerezHilton","text":"Rape, abuse, drugs, and more... members from Ricky Martin's boy band Menudo are speaking out: \nhttps://t.co/PLsmajx1h3","date":"Thu Jun 23 19:06:06 +0000 2022","user_id":"19329393"},{"handle":"PerezHilton","text":"A woman and her two dogs lost their lives in Los Angeles' terrifying lightning and thunderstorm this week -- DETAILS: \nhttps://t.co/hKNWZ95zKK","date":"Thu Jun 23 18:50:44 +0000 2022","user_id":"19329393"},{"handle":"PerezHilton","text":"This sounds super gross, but if Kim Kardashian can do it with Pete Davidson... #TheKardashians https://t.co/ylzibMtVLi","date":"Thu Jun 23 18:37:00 +0000 2022","user_id":"19329393"},{"handle":"PerezHilton","text":"Now how did Johnny Depp's name get dragged into the #GabbyPetito case?? https://t.co/TwbGFo2NIb","date":"Thu Jun 23 18:01:44 +0000 2022","user_id":"19329393"},{"handle":"PerezHilton","text":"It's official! Elon Musk's daughter has legally changed her name. NO MUSK! https://t.co/zSmuCKw8gj","date":"Thu Jun 23 17:55:10 +0000 2022","user_id":"19329393"},{"handle":"PerezHilton","text":"Do you think David Dobrik can beat this?? \nhttps://t.co/3FcStIrmrd","date":"Thu Jun 23 17:28:52 +0000 2022","user_id":"19329393"},{"handle":"PerezHilton","text":"Why does this whole story give #BigLittleLies vibes?? \nhttps://t.co/9dPCnNGOKz","date":"Thu Jun 23 17:07:11 +0000 2022","user_id":"19329393"},{"handle":"PerezHilton","text":"Peta Murgatroyd is giving fans a front row to her IVF journey! https://t.co/8MoqNI9HFb","date":"Thu Jun 23 16:52:28 +0000 2022","user_id":"19329393"},{"handle":"PerezHilton","text":"Taylor Swift is so in love!! https://t.co/8KOoTrpUaH","date":"Thu Jun 23 16:30:31 +0000 2022","user_id":"19329393"},{"handle":"PerezHilton","text":"Such a tragic accident. https://t.co/UDVvR82q4q","date":"Thu Jun 23 16:08:09 +0000 2022","user_id":"19329393"}]